dj_webhooks-0.2.1.dist-info/DESCRIPTION.rst
dj_webhooks-0.2.1.dist-info/METADATA
dj_webhooks-0.2.1.dist-info/metadata.json
dj_webhooks-0.2.1.dist-info/RECORD
dj_webhooks-0.2.1.dist-info/top_level.txt
dj_webhooks-0.2.1.dist-info/WHEEL
djwebhooks/__init__.py
djwebhooks/admin.py
djwebhooks/conf.py
djwebhooks/decorators.py
djwebhooks/models.py
djwebhooks/utils.py
djwebhooks/senders/__init__.py
djwebhooks/senders/celery.py
djwebhooks/senders/orm.py
djwebhooks/senders/redisq.py
djwebhooks/static/css/djwebhooks.css
djwebhooks/static/js/djwebhooks.js
djwebhooks/templates/djwebhooks/base.html
