Metadata-Version: 2.0
Name: dj-webhooks
Version: 0.2.1
Summary: Django + Webhooks Made Easy
Home-page: https://github.com/pydanny/dj-webhooks
Author: Daniel Greenfeld
Author-email: pydanny@gmail.com
License: BSD
Keywords: dj-webhooks
Platform: UNKNOWN
Classifier: Development Status :: 3 - Alpha
Classifier: Framework :: Django
Classifier: Intended Audience :: Developers
Classifier: License :: OSI Approved :: BSD License
Classifier: Natural Language :: English
Classifier: Programming Language :: Python :: 2.7
Classifier: Programming Language :: Python :: 3.3
Classifier: Programming Language :: Python :: 3.4
Requires-Dist: django (>=1.5.5)
Requires-Dist: webhooks (>=0.3.1)
Requires-Dist: django-jsonfield (>=0.9.12)
Requires-Dist: django-model-utils (>=2.0.2)
Requires-Dist: django-rq (>=0.6.1)
